reference_mcp/__init__.py
reference_mcp/server.py
reference_mcp-0.1.1.dist-info/METADATA
reference_mcp-0.1.1.dist-info/WHEEL
reference_mcp-0.1.1.dist-info/entry_points.txt
reference_mcp-0.1.1.dist-info/licenses/LICENSE
reference_mcp-0.1.1.dist-info/RECORD
