Metadata-Version: 2.4
Name: reference-mcp
Version: 0.1.1
Summary: Get citation data from CiteAs and Google Scholar
Project-URL: Homepage, https://github.com/ndchikin/reference-mcp
Project-URL: Repository, https://github.com/ndchikin/reference-mcp
Project-URL: Issues, https://github.com/ndchikin/reference-mcp/issues
License: MIT
License-File: LICENSE
Keywords: automation,git,llm,mcp
Requires-Python: >=3.11
Requires-Dist: mcp==1.4.1
Requires-Dist: scholarly==1.7.11
